ArcProbeInterface/__init__.py
ArcProbeInterface/asyncapi.py
ArcProbeInterface/baseapi.py
ArcProbeInterface/exceptions.py
ArcProbeInterface/syncapi.py
ArcProbeInterface/utils.py
ArcProbeInterface-0.1.4.dist-info/LICENSE
ArcProbeInterface-0.1.4.dist-info/METADATA
ArcProbeInterface-0.1.4.dist-info/WHEEL
ArcProbeInterface-0.1.4.dist-info/top_level.txt
ArcProbeInterface-0.1.4.dist-info/RECORD
